ecgkit/__init__.py
ecgkit/ECGRecord/ECGRecord.py
ecgkit/ECGRecord/__init__.py
ecgkit/denoise/__init__.py
ecgkit/denoise/denoise.py
ecgkit/denoise/kalman.py
ecgkit/detection/__init__.py
ecgkit/detection/beats_detection.py
ecgkit/detection/qrs_detection.py
ecgkit/ecg_generation/__init__.py
ecgkit/ecg_generation/generate_ecg_bvam.py
ecgkit/ecg_generation/generate_ecg_fhn.py
ecgkit/ecg_morphological/__init__.py
ecgkit/ecg_morphological/dynamic_system.py
ecgkit/ecg_morphological/sidl.py
ecgkit/ecg_plot/__init__.py
ecgkit/ecg_plot/ecg_plot.py
ecgkit-0.4.0.dist-info/METADATA
ecgkit-0.4.0.dist-info/WHEEL
ecgkit-0.4.0.dist-info/top_level.txt
ecgkit-0.4.0.dist-info/RECORD
